CHANGES.txt
LICENSE.txt
MANIFEST.in
README.txt
setup.py
docs/html/_sources/index.txt
docs/html/_sources/moving_parts.txt
docs/html/_sources/reference.txt
docs/html/_sources/tutorial.txt
docs/html/_sources/utilities.txt
src/pycounters/__init__.py
src/pycounters/base.py
src/pycounters/shortcuts.py
src/pycounters.egg-info/PKG-INFO
src/pycounters.egg-info/SOURCES.txt
src/pycounters.egg-info/dependency_links.txt
src/pycounters.egg-info/not-zip-safe
src/pycounters.egg-info/top_level.txt
src/pycounters/counters/__init__.py
src/pycounters/counters/base.py
src/pycounters/counters/mixins.py
src/pycounters/counters/types.py
src/pycounters/counters/values.py
src/pycounters/reporters/__init__.py
src/pycounters/reporters/base.py
src/pycounters/reporters/tcpcollection.py
src/pycounters/utils/__init__.py
src/pycounters/utils/munin.py
src/pycounters/utils/patcher.py
src/pycounters/utils/threads.py
src/pycounters/utils/timer.py