Metadata-Version: 1.0
Name: pycounters
Version: 0.7
Summary: PyCounters is a light weight library to monitor performance and events in production systems
Home-page: http://pycounters.readthedocs.org
Author: PyCounters Developers
Author-email: b.leskes@gmail.com
License: apache
Platform: UNKNOWN
